{
  "name": "Eula Rowe",
  "age": 24,
  "address": {
    "street": "Seufi Highway",
    "city": "Laliwhi",
    "state": "NM",
    "zip": "96786"
  },
  "contact": {
    "phone": "(782) 826-2267",
    "servicePhone": "800497279"
  },
  "birthday": "1971-07-07T07:19:55.740Z",
  "ip": "71.148.188.75",
  "foo": "bar",
  "profile": {
    "about": "Wo mepgoob golzarmi woj booczaf touhset salepjaf jueguzo dikof agezem rimdehnoz gu obozdiz sok ba odkupate mapu jepev. Nigiwej opezevgop pumeija gubac vuconmuw fowirus me cic ru wujcava zejfuk liv vamuaju wevail sag udbeze ecujec fabsobop. Nat notim imfu sopsucfe onefhab haki te piuwi vimnubsit hat kag ekpu ubkew papolo. Ciukhi igsoc pitfi lawjohbi zu votwujce pado fokapaki rap muwsakno woafa top.",
    "bio": "Eci sanpejjuv aknu epbil eb on ih uluveec pat mulka detecar guaroduh veefu gijib eko imuc li. Ikozarpef hagu esa la odmid dabok pofpi ju vavcotjer mufsutek dis mumbivdu ka ew sazkohih ilru ofiwe. Bukcemlum sumoga lut kidbun ci iku pekluizu ecaj do los wakfu ga mobica ose zup cih. Di jozo uc juvha uli piczo jectumu dubmacata hocva mida pul juvcop. Naziul johos nibetiv awnonom henriag newduf icdazvo gi put loemaru semioz ivjawo ru kahta pukokrij fit. Imdi keke juztifom pip sehtotefu uda sof utu we felmoj pa om ewa fulbulci cuut tuud. Riznafhig tocuvanov liog daker pa zeodeek vin mofdinbod rew tapef eviso eho rinsove kow fadfuf dodhed nocpes gi."
  },
  "apiKey": "83df433c1ffe5d25ff4b584c5a72523464b12db3deabfa8b8b9cf588ef772fd7",
  "currency": {
    "code": "SEK",
    "name": "Sweden Krona"
  }
}