{
  "name": "May Jefferson",
  "age": 33,
  "address": {
    "street": "Wokri Heights",
    "city": "Camaofu",
    "state": "SC",
    "zip": "25015"
  },
  "contact": {
    "phone": "(952) 618-9544",
    "servicePhone": "800827638"
  },
  "birthday": "2003-04-15T10:47:52.067Z",
  "ip": "197.72.89.176",
  "foo": "bar",
  "profile": {
    "about": "Lu zirewkic odube rabiz terepiram powuz ikwona ecduc jihe bucuto zacnekne gu. Gad wohuboje ru seda lalmid sobdivasi ilobo fu keer sug riesedo enawipla talhen sorukobi. Uve uzagogzik fecempi liufo bimulgiv rik dehho ko vusoj pet fow bepdiz ivusedah ho ufaeta. Mitru rij zig gif rewi wo aznujfo juc udi ruk cubunju kutaas ristic.",
    "bio": "Pafta poveapo funi overuke ersiodo ichag hevad kedig bisduba fu gam zad ipiwa coc vajcomfap duru bej. Utami esaev neji mizoki boon feeti al wubog uca vipesa cabej kiv guru bo. Ab ji apefaf ero vuvoazo teciila tetoren jibdoatu cof ne ci uvrakiw vof motujzoh cip val. Ubu jozlebac hani je jestaze jil nab mabceh cinanu kamveb kiihabu bundagji binhiklet sa wojwapuk je kih rolip. Go ewimiv woginju cujma nuuwe tilso vulnafa akaot oteto ros wigwi ida. Wi bawanhen uhunu enogihtol veg borucuk garde oke kopoke didmu ugtaor gojez ukaujuzi lozbinu tise nazre icbit be. Lu ilcuv udadehe vifjusew temke si rop ene ridko viwfuki nawo aze zi lob guc geogga."
  },
  "apiKey": "8a01272f928f553eeb513f589266e1f48811c8f992c93fc5990710b1b9cb82ff",
  "currency": {
    "code": "RSD",
    "name": "Serbia Dinar"
  }
}